Metadata-Version: 1.0
Name: tmdb3
Version: 0.7.2
Summary: TheMovieDB.org APIv3 interface
Home-page: UNKNOWN
Author: Raymond Wagner
Author-email: raymond@wagnerrp.com
License: UNKNOWN
Platform: UNKNOWN
